{"2873080":{"success":true,"data":{"type":"game","name":"不\/存在的你，和我","steam_appid":2873080,"required_age":0,"is_free":false,"dlc":[3639130],"detailed_description":"<p class=\"bb_paragraph\"><img class=\"bb_img\" src=\"https:\/\/shared.akamai.steamstatic.com\/store_item_assets\/steam\/apps\/2873080\/extras\/banner.png?t=1747102493\" \/><\/p><p class=\"bb_paragraph\"><img class=\"bb_img\" src=\"https:\/\/shared.akamai.steamstatic.com\/store_item_assets\/steam\/apps\/2873080\/extras\/part1.png?t=1747102493\" \/><\/p><p class=\"bb_paragraph\">这是一款带有超现实元素的心理恐怖短篇视觉小说，而你是这个游戏的主角。<\/p><p class=\"bb_paragraph\">某天，一位陌生的少女突然出现在了主角的房间中……<\/p><h2 class=\"bb_tag\">你要做的事情很简单<\/h2><p class=\"bb_paragraph\"><img class=\"bb_img\" src=\"https:\/\/shared.akamai.steamstatic.com\/store_item_assets\/steam\/apps\/2873080\/extras\/emo3.png?t=1747102493\" \/><\/p><ul class=\"bb_ul\"><li><p class=\"bb_paragraph\">和少女打个招呼~<\/p><\/li><\/ul><ul class=\"bb_ul\"><li><p class=\"bb_paragraph\">通过上百个选项对「少女的存在」做出回答。<\/p><\/li><\/ul><ul class=\"bb_ul\"><li><p class=\"bb_paragraph\">探寻「个体」的本质，发现「世界」的真相。<\/p><\/li><\/ul><h2 class=\"bb_tag\">而你要做的事情就更简单了，无非是<\/h2><p class=\"bb_paragraph\"><img class=\"bb_img\" src=\"https:\/\/shared.akamai.steamstatic.com\/store_item_assets\/steam\/apps\/2873080\/extras\/emo1.png?t=1747102493\" \/><\/p><ul class=\"bb_ul\"><li><p class=\"bb_paragraph\">和少女打个招呼~<\/p><\/li><\/ul><ul class=\"bb_ul\"><li><p class=\"bb_paragraph\">作为国王，聆听众卿的谏言，特别是那些「忠臣」的<strong>。<\/strong><\/p><\/li><li><p class=\"bb_paragraph\">制作草莓蛋糕，然后吃掉蛋糕，吃掉蛋糕，你真的会让少女吃掉蛋糕吗？<\/p><\/li><li><p class=\"bb_paragraph\">阻止FONTAINEBLEAU的阴谋，不要把时间机器交出去！<\/p><\/li><li><p class=\"bb_paragraph\">前往银葱之森打败魔王，完成逐梦者的使命。<\/p><\/li><li><p class=\"bb_paragraph\">在世界的尽头和少女约会。<\/p><\/li><li><p class=\"bb_paragraph\">品尝几颗药丸，顺便和这些药丸谈谈心。<\/p><\/li><li><p class=\"bb_paragraph\">见证你和少女的结局。<\/p><\/li><\/ul><p class=\"bb_paragraph\"><img class=\"bb_img\" src=\"https:\/\/shared.akamai.steamstatic.com\/store_item_assets\/steam\/apps\/2873080\/extras\/part2.png?t=1747102493\" \/><\/p><p class=\"bb_paragraph\"><img class=\"bb_img\" src=\"https:\/\/shared.akamai.steamstatic.com\/store_item_assets\/steam\/apps\/2873080\/extras\/lilith.png?t=1747102493\" \/><\/p><p class=\"bb_paragraph\"><i>这里才没有什么角色介绍。<\/i><\/p><p class=\"bb_paragraph\"><i>与其用标签化的词汇来定义我自己，我还是更希望我们在一起的时候，能够用经历和回忆去彼此感知和理解的呢。<\/i><\/p><p class=\"bb_paragraph\"><i>你因为你而存在，我因为我而存在。就这样，我们在此刻相遇......<\/i><\/p><p class=\"bb_paragraph\"><i>当然了，现在你对这句话的解读，你对我的感知......这何尝不是我的「自我介绍」呢？<\/i><\/p><p class=\"bb_paragraph\"><\/p><p class=\"bb_paragraph\"><img class=\"bb_img\" src=\"https:\/\/shared.akamai.steamstatic.com\/store_item_assets\/steam\/apps\/2873080\/extras\/sartre.png?t=1747102493\" \/><\/p><ul class=\"bb_ul\"><li><p class=\"bb_paragraph\"><i>个子小小，面带微笑。<\/i><\/p><\/li><\/ul><ul class=\"bb_ul\"><li><p class=\"bb_paragraph\"><i>钟情于撰写美少女游戏剧本的曼德拉草研究员。<\/i><\/p><\/li><\/ul><p class=\"bb_paragraph\"><\/p><p class=\"bb_paragraph\"><i><img class=\"bb_img\" src=\"https:\/\/shared.akamai.steamstatic.com\/store_item_assets\/steam\/apps\/2873080\/extras\/fouco.png?t=1747102493\" \/><\/i><\/p><ul class=\"bb_ul\"><li><p class=\"bb_paragraph\"><i>身材高挑，沉默寡言。<\/i><\/p><\/li><\/ul><ul class=\"bb_ul\"><li><p class=\"bb_paragraph\"><i>音游糕手但是↑↑↓↓←→←→BA(⁎˃ᴗ˂⁎)！<\/i><\/p><\/li><\/ul><p class=\"bb_paragraph\"><\/p><p class=\"bb_paragraph\"><\/p><p class=\"bb_paragraph\"><\/p><p class=\"bb_paragraph\"><\/p><p class=\"bb_paragraph\"><\/p><p class=\"bb_paragraph\"><i>当然了，以上这些或许都不是最重要的，重要的是……<\/i><\/p><p class=\"bb_paragraph\"><i>我希望你能够享受这段时光。<\/i><\/p><p class=\"bb_paragraph\"><img class=\"bb_img\" src=\"https:\/\/shared.akamai.steamstatic.com\/store_item_assets\/steam\/apps\/2873080\/extras\/emo2.png?t=1747102493\" \/><\/p><ul class=\"bb_ul\"><li><p class=\"bb_paragraph\">本游戏欢迎实况（包括创收性质的）~<\/p><\/li><\/ul><ul class=\"bb_ul\"><li><p class=\"bb_paragraph\">请在实况介绍页中加入《不\/存在的你，和我》的Steam主页链接，或是在实况中介绍本游戏。<\/p><\/li><\/ul>","about_the_game":"<p class=\"bb_paragraph\"><img class=\"bb_img\" src=\"https:\/\/shared.akamai.steamstatic.com\/store_item_assets\/steam\/apps\/2873080\/extras\/banner.png?t=1747102493\" \/><\/p><p class=\"bb_paragraph\"><img class=\"bb_img\" src=\"https:\/\/shared.akamai.steamstatic.com\/store_item_assets\/steam\/apps\/2873080\/extras\/part1.png?t=1747102493\" \/><\/p><p class=\"bb_paragraph\">这是一款带有超现实元素的心理恐怖短篇视觉小说，而你是这个游戏的主角。<\/p><p class=\"bb_paragraph\">某天，一位陌生的少女突然出现在了主角的房间中……<\/p><h2 class=\"bb_tag\">你要做的事情很简单<\/h2><p class=\"bb_paragraph\"><img class=\"bb_img\" src=\"https:\/\/shared.akamai.steamstatic.com\/store_item_assets\/steam\/apps\/2873080\/extras\/emo3.png?t=1747102493\" \/><\/p><ul class=\"bb_ul\"><li><p class=\"bb_paragraph\">和少女打个招呼~<\/p><\/li><\/ul><ul class=\"bb_ul\"><li><p class=\"bb_paragraph\">通过上百个选项对「少女的存在」做出回答。<\/p><\/li><\/ul><ul class=\"bb_ul\"><li><p class=\"bb_paragraph\">探寻「个体」的本质，发现「世界」的真相。<\/p><\/li><\/ul><h2 class=\"bb_tag\">而你要做的事情就更简单了，无非是<\/h2><p class=\"bb_paragraph\"><img class=\"bb_img\" src=\"https:\/\/shared.akamai.steamstatic.com\/store_item_assets\/steam\/apps\/2873080\/extras\/emo1.png?t=1747102493\" \/><\/p><ul class=\"bb_ul\"><li><p class=\"bb_paragraph\">和少女打个招呼~<\/p><\/li><\/ul><ul class=\"bb_ul\"><li><p class=\"bb_paragraph\">作为国王，聆听众卿的谏言，特别是那些「忠臣」的<strong>。<\/strong><\/p><\/li><li><p class=\"bb_paragraph\">制作草莓蛋糕，然后吃掉蛋糕，吃掉蛋糕，你真的会让少女吃掉蛋糕吗？<\/p><\/li><li><p class=\"bb_paragraph\">阻止FONTAINEBLEAU的阴谋，不要把时间机器交出去！<\/p><\/li><li><p class=\"bb_paragraph\">前往银葱之森打败魔王，完成逐梦者的使命。<\/p><\/li><li><p class=\"bb_paragraph\">在世界的尽头和少女约会。<\/p><\/li><li><p class=\"bb_paragraph\">品尝几颗药丸，顺便和这些药丸谈谈心。<\/p><\/li><li><p class=\"bb_paragraph\">见证你和少女的结局。<\/p><\/li><\/ul><p class=\"bb_paragraph\"><img class=\"bb_img\" src=\"https:\/\/shared.akamai.steamstatic.com\/store_item_assets\/steam\/apps\/2873080\/extras\/part2.png?t=1747102493\" \/><\/p><p class=\"bb_paragraph\"><img class=\"bb_img\" src=\"https:\/\/shared.akamai.steamstatic.com\/store_item_assets\/steam\/apps\/2873080\/extras\/lilith.png?t=1747102493\" \/><\/p><p class=\"bb_paragraph\"><i>这里才没有什么角色介绍。<\/i><\/p><p class=\"bb_paragraph\"><i>与其用标签化的词汇来定义我自己，我还是更希望我们在一起的时候，能够用经历和回忆去彼此感知和理解的呢。<\/i><\/p><p class=\"bb_paragraph\"><i>你因为你而存在，我因为我而存在。就这样，我们在此刻相遇......<\/i><\/p><p class=\"bb_paragraph\"><i>当然了，现在你对这句话的解读，你对我的感知......这何尝不是我的「自我介绍」呢？<\/i><\/p><p class=\"bb_paragraph\"><\/p><p class=\"bb_paragraph\"><img class=\"bb_img\" src=\"https:\/\/shared.akamai.steamstatic.com\/store_item_assets\/steam\/apps\/2873080\/extras\/sartre.png?t=1747102493\" \/><\/p><ul class=\"bb_ul\"><li><p class=\"bb_paragraph\"><i>个子小小，面带微笑。<\/i><\/p><\/li><\/ul><ul class=\"bb_ul\"><li><p class=\"bb_paragraph\"><i>钟情于撰写美少女游戏剧本的曼德拉草研究员。<\/i><\/p><\/li><\/ul><p class=\"bb_paragraph\"><\/p><p class=\"bb_paragraph\"><i><img class=\"bb_img\" src=\"https:\/\/shared.akamai.steamstatic.com\/store_item_assets\/steam\/apps\/2873080\/extras\/fouco.png?t=1747102493\" \/><\/i><\/p><ul class=\"bb_ul\"><li><p class=\"bb_paragraph\"><i>身材高挑，沉默寡言。<\/i><\/p><\/li><\/ul><ul class=\"bb_ul\"><li><p class=\"bb_paragraph\"><i>音游糕手但是↑↑↓↓←→←→BA(⁎˃ᴗ˂⁎)！<\/i><\/p><\/li><\/ul><p class=\"bb_paragraph\"><\/p><p class=\"bb_paragraph\"><\/p><p class=\"bb_paragraph\"><\/p><p class=\"bb_paragraph\"><\/p><p class=\"bb_paragraph\"><\/p><p class=\"bb_paragraph\"><i>当然了，以上这些或许都不是最重要的，重要的是……<\/i><\/p><p class=\"bb_paragraph\"><i>我希望你能够享受这段时光。<\/i><\/p><p class=\"bb_paragraph\"><img class=\"bb_img\" src=\"https:\/\/shared.akamai.steamstatic.com\/store_item_assets\/steam\/apps\/2873080\/extras\/emo2.png?t=1747102493\" \/><\/p><ul class=\"bb_ul\"><li><p class=\"bb_paragraph\">本游戏欢迎实况（包括创收性质的）~<\/p><\/li><\/ul><ul class=\"bb_ul\"><li><p class=\"bb_paragraph\">请在实况介绍页中加入《不\/存在的你，和我》的Steam主页链接，或是在实况中介绍本游戏。<\/p><\/li><\/ul>","short_description":"以「游戏」为载体展现「你\/少女」的世界。 以「视觉小说」为表现形式探索「你\/少女\/世界」的真相。","supported_languages":"简体中文<strong>*<\/strong>, 英语, 日语<strong>*<\/strong>, 繁体中文<strong>*<\/strong>, 俄语, 印度尼西亚语, 葡萄牙语 - 巴西, 乌克兰语, 韩语, 西班牙语 - 拉丁美洲<br><strong>*<\/strong>具有完全音频支持的语言","header_image":"https:\/\/shared.akamai.steamstatic.com\/store_item_assets\/steam\/apps\/2873080\/header_schinese.jpg?t=1747102493","capsule_image":"https:\/\/shared.akamai.steamstatic.com\/store_item_assets\/steam\/apps\/2873080\/ffa13140acee42cfb6fac993229c3d07727d17b8\/capsule_231x87_schinese.jpg?t=1747102493","capsule_imagev5":"https:\/\/shared.akamai.steamstatic.com\/store_item_assets\/steam\/apps\/2873080\/ffa13140acee42cfb6fac993229c3d07727d17b8\/capsule_184x69_schinese.jpg?t=1747102493","website":null,"pc_requirements":{"minimum":"<strong>最低配置:<\/strong><br><ul class=\"bb_ul\"><li><strong>操作系统:<\/strong> 几乎任意版本的Windows都可以<br><\/li><li><strong>处理器:<\/strong> 如果你的电脑能启动，那大概是没问题的<br><\/li><li><strong>内存:<\/strong> 4 GB RAM<br><\/li><li><strong>显卡:<\/strong> 如果你能在电脑上看到这行字，那大概也是没问题的<br><\/li><li><strong>存储空间:<\/strong> 需要 2048 MB 可用空间<br><\/li><li><strong>声卡:<\/strong> 如果你的电脑能够听音乐，那大概是更没有问题的<\/li><\/ul>"},"mac_requirements":{"minimum":"<strong>最低配置:<\/strong><br><ul class=\"bb_ul\"><li><strong>操作系统:<\/strong> 几乎任意版本的macOS都可以<br><\/li><li><strong>处理器:<\/strong> 如果你的电脑能启动，那大概是没问题的<br><\/li><li><strong>内存:<\/strong> 4 GB RAM<br><\/li><li><strong>显卡:<\/strong> 如果你能在电脑上看到这行字，那大概也是没问题的<br><\/li><li><strong>存储空间:<\/strong> 需要 2048 MB 可用空间<br><\/li><li><strong>声卡:<\/strong> 如果你的电脑能够听音乐，那大概是更没有问题的<\/li><\/ul>"},"linux_requirements":[],"developers":["Fontainebleau"],"publishers":["Nino Games"],"price_overview":{"currency":"USD","initial":199,"final":179,"discount_percent":10,"initial_formatted":"$1.99","final_formatted":"$1.79"},"packages":[1024561],"package_groups":[{"name":"default","title":"购买 不\/存在的你，和我","description":"","selection_text":"选择一个购买选项","save_text":"","display_type":0,"is_recurring_subscription":"false","subs":[{"packageid":1024561,"percent_savings_text":"-10% ","percent_savings":0,"option_text":"不\/存在的你，和我 - <span class=\"discount_original_price\">$1.99<\/span> $1.79","option_description":"","can_get_free_license":"0","is_free_license":false,"price_in_cents_with_discount":179}]}],"platforms":{"windows":true,"mac":true,"linux":false},"categories":[{"id":2,"description":"单人"},{"id":22,"description":"Steam 成就"},{"id":29,"description":"Steam 集换式卡牌"},{"id":23,"description":"Steam 云"},{"id":62,"description":"家庭共享"}],"genres":[{"id":"25","description":"冒险"},{"id":"23","description":"独立"},{"id":"3","description":"角色扮演"}],"screenshots":[{"id":0,"path_thumbnail":"https:\/\/shared.akamai.steamstatic.com\/store_item_assets\/steam\/apps\/2873080\/ss_18337ee5e084b2cdb61c535eeff49332a8f94b9b.600x338.jpg?t=1747102493","path_full":"https:\/\/shared.akamai.steamstatic.com\/store_item_assets\/steam\/apps\/2873080\/ss_18337ee5e084b2cdb61c535eeff49332a8f94b9b.1920x1080.jpg?t=1747102493"},{"id":1,"path_thumbnail":"https:\/\/shared.akamai.steamstatic.com\/store_item_assets\/steam\/apps\/2873080\/ss_92958310150b71b6dfe7cbb73f03780418183864.600x338.jpg?t=1747102493","path_full":"https:\/\/shared.akamai.steamstatic.com\/store_item_assets\/steam\/apps\/2873080\/ss_92958310150b71b6dfe7cbb73f03780418183864.1920x1080.jpg?t=1747102493"},{"id":2,"path_thumbnail":"https:\/\/shared.akamai.steamstatic.com\/store_item_assets\/steam\/apps\/2873080\/ss_575a02e1d8c799ddeb5f4136f5c9251884941388.600x338.jpg?t=1747102493","path_full":"https:\/\/shared.akamai.steamstatic.com\/store_item_assets\/steam\/apps\/2873080\/ss_575a02e1d8c799ddeb5f4136f5c9251884941388.1920x1080.jpg?t=1747102493"},{"id":3,"path_thumbnail":"https:\/\/shared.akamai.steamstatic.com\/store_item_assets\/steam\/apps\/2873080\/ss_08528b5acc3bb31879ee7e0e9c326b6579813a5f.600x338.jpg?t=1747102493","path_full":"https:\/\/shared.akamai.steamstatic.com\/store_item_assets\/steam\/apps\/2873080\/ss_08528b5acc3bb31879ee7e0e9c326b6579813a5f.1920x1080.jpg?t=1747102493"},{"id":4,"path_thumbnail":"https:\/\/shared.akamai.steamstatic.com\/store_item_assets\/steam\/apps\/2873080\/ss_ba88ce59fc36e12f7670f8aff68f6952e5cce2f0.600x338.jpg?t=1747102493","path_full":"https:\/\/shared.akamai.steamstatic.com\/store_item_assets\/steam\/apps\/2873080\/ss_ba88ce59fc36e12f7670f8aff68f6952e5cce2f0.1920x1080.jpg?t=1747102493"},{"id":5,"path_thumbnail":"https:\/\/shared.akamai.steamstatic.com\/store_item_assets\/steam\/apps\/2873080\/ss_510eb95697675115c30fea0898c597a4bee7f801.600x338.jpg?t=1747102493","path_full":"https:\/\/shared.akamai.steamstatic.com\/store_item_assets\/steam\/apps\/2873080\/ss_510eb95697675115c30fea0898c597a4bee7f801.1920x1080.jpg?t=1747102493"},{"id":6,"path_thumbnail":"https:\/\/shared.akamai.steamstatic.com\/store_item_assets\/steam\/apps\/2873080\/ss_a6162f3e9d7a3b6063b2fafef813ce723d65c376.600x338.jpg?t=1747102493","path_full":"https:\/\/shared.akamai.steamstatic.com\/store_item_assets\/steam\/apps\/2873080\/ss_a6162f3e9d7a3b6063b2fafef813ce723d65c376.1920x1080.jpg?t=1747102493"},{"id":7,"path_thumbnail":"https:\/\/shared.akamai.steamstatic.com\/store_item_assets\/steam\/apps\/2873080\/ss_666e4369c3f63af050ac9e732de2816a230aca1f.600x338.jpg?t=1747102493","path_full":"https:\/\/shared.akamai.steamstatic.com\/store_item_assets\/steam\/apps\/2873080\/ss_666e4369c3f63af050ac9e732de2816a230aca1f.1920x1080.jpg?t=1747102493"},{"id":8,"path_thumbnail":"https:\/\/shared.akamai.steamstatic.com\/store_item_assets\/steam\/apps\/2873080\/ss_a1226b3fab84f1f8fe501cb6c1975140748891d7.600x338.jpg?t=1747102493","path_full":"https:\/\/shared.akamai.steamstatic.com\/store_item_assets\/steam\/apps\/2873080\/ss_a1226b3fab84f1f8fe501cb6c1975140748891d7.1920x1080.jpg?t=1747102493"},{"id":9,"path_thumbnail":"https:\/\/shared.akamai.steamstatic.com\/store_item_assets\/steam\/apps\/2873080\/ss_363267b533c8439e221e366e25f97dcc46317b3a.600x338.jpg?t=1747102493","path_full":"https:\/\/shared.akamai.steamstatic.com\/store_item_assets\/steam\/apps\/2873080\/ss_363267b533c8439e221e366e25f97dcc46317b3a.1920x1080.jpg?t=1747102493"}],"movies":[{"id":257081934,"name":"游戏实机片段~","thumbnail":"https:\/\/shared.akamai.steamstatic.com\/store_item_assets\/steam\/apps\/257081934\/a2456966fb25eaf904e7bc6e34584a95b0dda7a5\/movie_600x337.jpg?t=1734106700","webm":{"480":"http:\/\/video.akamai.steamstatic.com\/store_trailers\/257081934\/movie480_vp9.webm?t=1734106700","max":"http:\/\/video.akamai.steamstatic.com\/store_trailers\/257081934\/movie_max_vp9.webm?t=1734106700"},"mp4":{"480":"http:\/\/video.akamai.steamstatic.com\/store_trailers\/257081934\/movie480.mp4?t=1734106700","max":"http:\/\/video.akamai.steamstatic.com\/store_trailers\/257081934\/movie_max.mp4?t=1734106700"},"highlight":true},{"id":257081305,"name":"Just Lilith","thumbnail":"https:\/\/shared.akamai.steamstatic.com\/store_item_assets\/steam\/apps\/257081305\/d87eacaf752428021df2c3a203bf603dff091d3f\/movie_600x337.jpg?t=1734106713","webm":{"480":"http:\/\/video.akamai.steamstatic.com\/store_trailers\/257081305\/movie480_vp9.webm?t=1734106713","max":"http:\/\/video.akamai.steamstatic.com\/store_trailers\/257081305\/movie_max_vp9.webm?t=1734106713"},"mp4":{"480":"http:\/\/video.akamai.steamstatic.com\/store_trailers\/257081305\/movie480.mp4?t=1734106713","max":"http:\/\/video.akamai.steamstatic.com\/store_trailers\/257081305\/movie_max.mp4?t=1734106713"},"highlight":true}],"recommendations":{"total":5558},"achievements":{"total":31,"highlighted":[{"name":"视觉小说糕手！","path":"https:\/\/cdn.akamai.steamstatic.com\/steamcommunity\/public\/images\/apps\/2873080\/245c7d37f696cfcd409d5e43c9dfb77b304fb96a.jpg"},{"name":"继续游戏","path":"https:\/\/cdn.akamai.steamstatic.com\/steamcommunity\/public\/images\/apps\/2873080\/e20cf918fa19bb5147843fbcb74c993aa84d86ce.jpg"},{"name":"失去的回忆","path":"https:\/\/cdn.akamai.steamstatic.com\/steamcommunity\/public\/images\/apps\/2873080\/56f0db4e202dd4f9237bda076bcc06435fee99a3.jpg"},{"name":"打开新世界的大门","path":"https:\/\/cdn.akamai.steamstatic.com\/steamcommunity\/public\/images\/apps\/2873080\/6f07221979871f44b8a1554087ba8f97583fd73f.jpg"},{"name":"掌握未来女神计划","path":"https:\/\/cdn.akamai.steamstatic.com\/steamcommunity\/public\/images\/apps\/2873080\/8e426bb6c7639e39185e3279e262a7feb656759f.jpg"},{"name":"「描绘」","path":"https:\/\/cdn.akamai.steamstatic.com\/steamcommunity\/public\/images\/apps\/2873080\/15a019f086dad7b6c57c92484036101fbd18c4b8.jpg"},{"name":"你的游戏，她的世界","path":"https:\/\/cdn.akamai.steamstatic.com\/steamcommunity\/public\/images\/apps\/2873080\/811d214d34654d32ecdf279103365c1a298b1468.jpg"},{"name":"美味时刻","path":"https:\/\/cdn.akamai.steamstatic.com\/steamcommunity\/public\/images\/apps\/2873080\/b27c092b2db218ae4e41f3b52be83bfe0048503d.jpg"},{"name":"甜蜜的蛋糕时间","path":"https:\/\/cdn.akamai.steamstatic.com\/steamcommunity\/public\/images\/apps\/2873080\/78e20e736fd46007cb3d04bdee808ee351615d3d.jpg"},{"name":"不存在的","path":"https:\/\/cdn.akamai.steamstatic.com\/steamcommunity\/public\/images\/apps\/2873080\/862ce98ff2eb6befc3086915ec2da78d58bd4429.jpg"}]},"release_date":{"coming_soon":false,"date":"2024 年 12 月 15 日"},"support_info":{"url":"","email":"yukitobi233@gmail.com"},"background":"https:\/\/store.akamai.steamstatic.com\/images\/storepagebackground\/app\/2873080?t=1747102493","background_raw":"https:\/\/shared.akamai.steamstatic.com\/store_item_assets\/steam\/apps\/2873080\/page_bg_raw.jpg?t=1747102493","content_descriptors":{"ids":[],"notes":null},"ratings":{"dejus":{"rating_generated":"1","rating":"12","required_age":"12","banned":"0","use_age_gate":"0","descriptors":"Violência"},"steam_germany":{"rating_generated":"1","rating":"16","required_age":"16","banned":"0","use_age_gate":"0","descriptors":"Gewalt"}}}}}